example_package_ryanjob42/__init__.py
example_package_ryanjob42/example.py
example_package_ryanjob42-0.0.2.dist-info/METADATA
example_package_ryanjob42-0.0.2.dist-info/WHEEL
example_package_ryanjob42-0.0.2.dist-info/licenses/LICENSE
example_package_ryanjob42-0.0.2.dist-info/RECORD
